LICENSE
MANIFEST.in
README.rst
setup.py
pipetools/__init__.py
pipetools/compat.py
pipetools/debug.py
pipetools/decorators.py
pipetools/ds_builder.py
pipetools/main.py
pipetools/utils.py
pipetools.egg-info/PKG-INFO
pipetools.egg-info/SOURCES.txt
pipetools.egg-info/dependency_links.txt
pipetools.egg-info/requires.txt
pipetools.egg-info/top_level.txt