Metadata-Version: 1.1
Name: pipetools
Version: 1.0.1
Summary: A library that enables function composition similar to using Unix pipes.
Home-page: https://0101.github.io/pipetools/
Author: Petr Pokorny
Author-email: petr@innit.cz
License: MIT
Platform: UNKNOWN
Classifier: Development Status :: 5 - Production/Stable
Classifier: Intended Audience :: Developers
Classifier: License :: OSI Approved :: MIT License
Classifier: Operating System :: OS Independent
Classifier: Programming Language :: Python :: 2
Classifier: Programming Language :: Python :: 3
Classifier: Topic :: Utilities
